lib/__init__.py
lib/navjot.py
Topsis_navjot_102103455-0.0.1.dist-info/METADATA
Topsis_navjot_102103455-0.0.1.dist-info/WHEEL
Topsis_navjot_102103455-0.0.1.dist-info/top_level.txt
Topsis_navjot_102103455-0.0.1.dist-info/RECORD
