Metadata-Version: 2.1
Name: Topsis-navjot-102103455
Version: 0.0.1
Summary: topsis package
Author: navjot
Author-email: brarnavjot137@gmail.com
Keywords: python,video,stream,video stream,camera stream,sockets
Classifier: Development Status :: 1 - Planning
Classifier: Intended Audience :: Developers
Classifier: Programming Language :: Python :: 3
Classifier: Operating System :: Unix
Classifier: Operating System :: MacOS :: MacOS X
Classifier: Operating System :: Microsoft :: Windows
Requires-Dist: logging
Requires-Dist: numpy
Requires-Dist: pandas
